Metadata-Version: 2.4
Name: mcp-server-math
Version: 0.1.0
Summary: A MCP server providing LLM with various mathematical capabilities
Project-URL: Homepage, https://github.com/jiaxinzhang18/mcp-server-math
Project-URL: Issues, https://github.com/jiaxinzhang18/mcp-server-math/issues
Author-email: Jiaxin Zhang <jiaxinzhang18@gmail.com>
License-File: LICENSE
Classifier: License :: OSI Approved :: MIT License
Classifier: Operating System :: OS Independent
Classifier: Programming Language :: Python :: 3
Requires-Python: >=3.10
Requires-Dist: mcp[cli]>=1.6.0
Requires-Dist: pydantic
